{"cameraMode":{"drawMode":0,"name":"Shaded","section":"Shading Mode"},"sceneLighting":true,"audioPlay":false,"sceneViewState":{"m_AlwaysRefresh":false,"showFog":true,"showSkybox":true,"showFlares":true,"showImageEffects":true,"showParticleSystems":true,"showVisualEffectGraphs":true,"m_FxEnabled":true},"in2DMode":false,"pivot":{"x":-76.688232421875,"y":-55.26377868652344,"z":22.897003173828126},"rotation":{"x":-0.2425738275051117,"y":0.612742006778717,"z":-0.20533931255340577,"w":-0.7236234545707703},"size":64.78292846679688,"orthographic":false}